{"Asian American Alliance (East Asian Branch)":{"name":"Asian American Alliance (East Asian Branch)","studentLeaders":"unknown","advisors":"unknown","description":"enter here"},"Asian American Alliance (South Asian Branch)":{"name":"Asian American Alliance (South Asian Branch)","studentLeaders":"unknown","advisors":"unknown","description":"enter here"}, "Black Affairs Club":{"name":"Black Affairs Club)","studentLeaders":"unknown","advisors":"unknown","description":"enter here"}, "Gender Sexuality Alliance":{"name":"Gender Sexuality Alliance","studentLeaders":"unknown","advisors":"unknown","description":"enter here"}}
